amazoncaptcha_api/__init__.py
amazoncaptcha_api/__main__.py
amazoncaptcha_api/app.py
amazoncaptcha_api/test_app.py
amazoncaptcha_api-0.0.3.dist-info/LICENSE
amazoncaptcha_api-0.0.3.dist-info/METADATA
amazoncaptcha_api-0.0.3.dist-info/WHEEL
amazoncaptcha_api-0.0.3.dist-info/top_level.txt
amazoncaptcha_api-0.0.3.dist-info/RECORD
