Metadata-Version: 2.1
Name: amazoncaptcha-api
Version: 0.0.3
Summary: Simple anti-captcha compatable API (createTask/getTaskResult) to solve the Amazon's text captcha for free
Home-page: https://github.com/melehin/amazoncaptcha-api
Author: Fedor Melekhin
Author-email: fedormelexin@gmail.com
License: UNKNOWN
Platform: UNKNOWN
Classifier: Programming Language :: Python :: 3
Classifier: License :: OSI Approved :: MIT License
Classifier: Operating System :: OS Independent
Requires-Python: >=3.6
Requires-Dist: flask
Requires-Dist: amazoncaptcha
Requires-Dist: requests
Requires-Dist: gunicorn
